mpesa/__init__.py
mpesa/drc/__init__.py
mpesa/drc/callback_parser.py
mpesa/drc/generators.py
mpesa/drc/parsers.py
mpesa/drc/request_parser.py
mpesa/egypt/__init__.py
mpesa/ghana/__init__.py
mpesa/kenya/__init__.py
mpesa/lesotho/__init__.py
mpesa/mozambique/__init__.py
mpesa/portalsdk/__init__.py
mpesa/portalsdk/api.py
mpesa/tanzania/__init__.py
mpesa/tests/__init__.py
mpesa/tests/drc/__init__.py
mpesa/tests/egypt/__init__.py
mpesa/tests/ghana/__init__.py
mpesa/tests/kenya/__init__.py
mpesa/tests/lesotho/__init__.py
mpesa/tests/mozambique/__init__.py
mpesa/tests/tanzania/__init__.py
tekmpesa-1.0.2.dist-info/METADATA
tekmpesa-1.0.2.dist-info/WHEEL
tekmpesa-1.0.2.dist-info/entry_points.txt
tekmpesa-1.0.2.dist-info/top_level.txt
tekmpesa-1.0.2.dist-info/RECORD
