Metadata-Version: 2.1
Name: tekmpesa
Version: 1.0.2
Summary: All Mpesa APIs for All 8 Countries
Home-page: https://github.com/TralahM/tekmpesa
Author: Tralah M Brian
Author-email: musyoki.brian@tralahtek.com
License: GPLV3
Project-URL: Source, https://github.com/TralahM/tekmpesa
Project-URL: Tracker, https://github.com/TralahM/tekmpesa/issues
Project-URL: Documentation, https://github.com/TralahM/tekmpesa
Platform: UNKNOWN
Classifier: Environment :: Web Environment
Classifier: Intended Audience :: Developers
Classifier: License :: OSI Approved :: GNU General Public License v3 (GPLv3)
Classifier: Operating System :: OS Independent
Classifier: Programming Language :: Python
Classifier: Programming Language :: Python :: 3
Classifier: Programming Language :: Python :: 3 :: Only
Classifier: Programming Language :: Python :: 3.6
Classifier: Programming Language :: Python :: 3.7
Classifier: Programming Language :: Python :: 3.8
Classifier: Topic :: Internet :: WWW/HTTP
Classifier: Topic :: Internet :: WWW/HTTP :: Dynamic Content
Requires-Dist: requests
Requires-Dist: urllib3
Requires-Dist: pycryptodome
Requires-Dist: certifi
Requires-Dist: chardet
Requires-Dist: idna
Requires-Dist: six
Requires-Dist: pytest
Requires-Dist: future
Requires-Dist: jinja2
Requires-Dist: lxml
Requires-Dist: PyYaml
Requires-Dist: xmltodict
Provides-Extra: docs
Requires-Dist: sphinx ; extra == 'docs'
Requires-Dist: sphinx-automodapi ; extra == 'docs'
